partial_json_fixer-0.5.3.dist-info/METADATA
partial_json_fixer-0.5.3.dist-info/WHEEL
partial_json_fixer/__init__.py
partial_json_fixer/partial_json_fixer.cpython-310-i386-linux-gnu.so
partial_json_fixer-0.5.3.dist-info/RECORD
